flask_profiler/__init__.py
flask_profiler/flask_profiler.py
flask_profiler/static/dist/index.html
flask_profiler/static/dist/css/main.css
flask_profiler/static/dist/fonts/glyphicons-halflings-regular.eot
flask_profiler/static/dist/fonts/glyphicons-halflings-regular.svg
flask_profiler/static/dist/fonts/glyphicons-halflings-regular.ttf
flask_profiler/static/dist/fonts/glyphicons-halflings-regular.woff
flask_profiler/static/dist/images/python-flask.png
flask_profiler/static/dist/js/main.js
flask_profiler/static/dist/js/settings.js
flask_profiler/static/dist/js/vendor.js
flask_profiler/storage/__init__.py
flask_profiler/storage/base.py
flask_profiler/storage/logengine.py
flask_profiler/storage/mongo.py
flask_profiler/storage/sql_alchemy.py
flask_profiler/storage/sqlite.py
flask_profiler_logger-1.0.dist-info/DESCRIPTION.rst
flask_profiler_logger-1.0.dist-info/METADATA
flask_profiler_logger-1.0.dist-info/RECORD
flask_profiler_logger-1.0.dist-info/WHEEL
flask_profiler_logger-1.0.dist-info/metadata.json
flask_profiler_logger-1.0.dist-info/top_level.txt
