Metadata-Version: 2.0
Name: flask-profiler-logger
Version: 1.0
Summary: API endpoint profiler for Flask framework
Home-page: https://github.com/saivarunr/flask-profiler
Author: Sai Varun Reddy Daram
Author-email: saivarunvishal@gmail.com
License: The MIT License (MIT)
Requires-Dist: Flask
Requires-Dist: Flask-HTTPAuth
Requires-Dist: simplejson
